httoop/__init__.py
httoop/__main__.py
httoop/date.py
httoop/exceptions.py
httoop/meta.py
httoop/parser.py
httoop/six.py
httoop/test.py
httoop/util.py
httoop/version.py
httoop/authentication/__init__.py
httoop/authentication/basic.py
httoop/authentication/digest.py
httoop/cache/__init__.py
httoop/client/__init__.py
httoop/codecs/__init__.py
httoop/codecs/codec.py
httoop/codecs/application/__init__.py
httoop/codecs/application/gzip.py
httoop/codecs/application/hal_json.py
httoop/codecs/application/json.py
httoop/codecs/application/x_www_form_urlencoded.py
httoop/codecs/application/xml.py
httoop/codecs/application/zlib.py
httoop/codecs/audio/__init__.py
httoop/codecs/example/__init__.py
httoop/codecs/image/__init__.py
httoop/codecs/message/__init__.py
httoop/codecs/message/http.py
httoop/codecs/model/__init__.py
httoop/codecs/multipart/__init__.py
httoop/codecs/multipart/multipart.py
httoop/codecs/text/__init__.py
httoop/codecs/text/html.py
httoop/codecs/text/plain.py
httoop/codecs/video/__init__.py
httoop/gateway/__init__.py
httoop/gateway/wsgi.py
httoop/header/__init__.py
httoop/header/auth.py
httoop/header/cache.py
httoop/header/conditional.py
httoop/header/element.py
httoop/header/headers.py
httoop/header/messaging.py
httoop/header/range.py
httoop/header/security.py
httoop/header/semantics.py
httoop/messages/__init__.py
httoop/messages/body.py
httoop/messages/message.py
httoop/messages/method.py
httoop/messages/protocol.py
httoop/messages/request.py
httoop/messages/response.py
httoop/proxy/__init__.py
httoop/semantic/__init__.py
httoop/semantic/message.py
httoop/semantic/request.py
httoop/semantic/response.py
httoop/server/__init__.py
httoop/status/__init__.py
httoop/status/client_error.py
httoop/status/informational.py
httoop/status/redirect.py
httoop/status/server_error.py
httoop/status/status.py
httoop/status/success.py
httoop/status/types.py
httoop/uri/__init__.py
httoop/uri/http.py
httoop/uri/percent_encoding.py
httoop/uri/query_string.py
httoop-0.1.1.dist-info/LICENSE
httoop-0.1.1.dist-info/METADATA
httoop-0.1.1.dist-info/WHEEL
httoop-0.1.1.dist-info/top_level.txt
httoop-0.1.1.dist-info/zip-safe
httoop-0.1.1.dist-info/RECORD
